{"karmel": {"lang": "es", "friends_list": {"male_rate": "19%", "MrAlanCooper": {"lang": "en", "favourites_count": 24862, "name": "Alan Cooper", "friends_count": 959, "gender": "male", "followers_count": 25341, "location": "San Francisco CA, Petaluma CA", "statuses_count": 35416, "id": 103920270}, "caroramsey": {"lang": "en", "favourites_count": 35686, "name": "caro ramsey \ud83c\udf54", "friends_count": 387, "gender": "undetermined", "followers_count": 6596, "location": "Boston, MA", "statuses_count": 48897, "id": 74318663}, "AndaluciaTECH": {"lang": "en", "favourites_count": 1687, "name": "Andalucia TECH", "friends_count": 705, "gender": "undetermined", "followers_count": 3539, "location": "Spain", "statuses_count": 3534, "id": 228317338}, "alvarohernandec": {"lang": "es", "favourites_count": 5648, "name": "Alvaro Hernandez", "friends_count": 460, "gender": "male", "followers_count": 960, "location": "Almeriense murciano de M\u00e1laga", "statuses_count": 9160, "id": 259958479}, "ProPublica": {"lang": "en", "favourites_count": 3359, "name": "ProPublica", "friends_count": 289, "gender": "undetermined", "followers_count": 654228, "location": "New York, NY", "statuses_count": 46444, "id": 14606079}, "milesandagile": {"lang": "en", "favourites_count": 460, "name": "Juan P\u00e9rez", "friends_count": 406, "gender": "male", "followers_count": 2187, "location": "Spain and beyond", "statuses_count": 1157, "id": 26085565}, "pedroveraOyP": {"lang": "es", "favourites_count": 47868, "name": "Pedro Vera", "friends_count": 650, "gender": "male", "followers_count": 32757, "location": "Murcia", "statuses_count": 66834, "id": 110117638}, "RPHuidobro": {"lang": "es", "favourites_count": 1846, "name": "R.P.Huidobro", "friends_count": 495, "gender": "undetermined", "followers_count": 635, "location": "London", "statuses_count": 9262, "id": 30928593}, "nachocoloma": {"lang": "en", "favourites_count": 2791, "name": "Nacho Coloma", "friends_count": 70, "gender": "male", "followers_count": 1293, "location": "Berlin, Germany", "statuses_count": 5383, "id": 137111012}, "uxmag": {"lang": "en", "favourites_count": 178, "name": "UX Magazine", "friends_count": 7577, "gender": "undetermined", "followers_count": 186115, "location": "", "statuses_count": 5874, "id": 15056788}, "ana_valdi": {"lang": "ca", "favourites_count": 1400, "name": "Ana Valdivia", "friends_count": 770, "gender": "female", "followers_count": 414, "location": "On Earth", "statuses_count": 2107, "id": 294101019}, "Bi_FelgtB": {"lang": "es", "favourites_count": 1076, "name": "Bisexuales FELGTB", "friends_count": 554, "gender": "undetermined", "followers_count": 2118, "location": "", "statuses_count": 1915, "id": 1951674986}, "geekandtechgirl": {"lang": "es", "favourites_count": 576, "name": "Geek & Tech Girls", "friends_count": 398, "gender": "undetermined", "followers_count": 715, "location": "Granada, Espa\u00f1a", "statuses_count": 1182, "id": 783584842277609472}, "ernestopimentel": {"lang": "en", "favourites_count": 6, "name": "Ernesto Pimentel", "friends_count": 78, "gender": "male", "followers_count": 268, "location": "M\u00e1laga", "statuses_count": 14, "id": 99142037}, "data4change": {"lang": "en-gb", "favourites_count": 15, "name": "data4change", "friends_count": 265, "gender": "undetermined", "followers_count": 185, "location": "London, England", "statuses_count": 43, "id": 3300885028}, "pixelinmind": {"lang": "es", "favourites_count": 154, "name": "Alberto Garc\u00eda", "friends_count": 316, "gender": "male", "followers_count": 139, "location": "Madrid, Spain", "statuses_count": 546, "id": 136025942}, "JoseAntPR": {"lang": "es", "favourites_count": 1137, "name": "Jose Antonio", "friends_count": 317, "gender": "male", "followers_count": 385, "location": "M\u00e1laga", "statuses_count": 476, "id": 381150181}, "mambanegra86": {"lang": "es", "favourites_count": 616, "name": "Alicia Garc\u00eda", "friends_count": 190, "gender": "female", "followers_count": 389, "location": "Salamanca", "statuses_count": 4269, "id": 59621538}, "pedroterrero": {"lang": "es", "favourites_count": 153, "name": "Pedro Terrero", "friends_count": 268, "gender": "male", "followers_count": 229, "location": "M\u00e1laga", "statuses_count": 484, "id": 270522128}, "lourdes_marco_": {"lang": "es", "favourites_count": 1198, "name": "Lourdes Marco", "friends_count": 774, "gender": "female", "followers_count": 308, "location": "Madrid, Comunidad de Madrid", "statuses_count": 1027, "id": 1177089968}, "Dagsdotter": {"lang": "es", "favourites_count": 1770, "name": "Johanna Forssell", "friends_count": 1824, "gender": "female", "followers_count": 1342, "location": "Fuengirola", "statuses_count": 7822, "id": 215046086}, "ClarisseIsidoro": {"lang": "es", "favourites_count": 57925, "name": "ClarisseBradbury", "friends_count": 3373, "gender": "undetermined", "followers_count": 3527, "location": " Don't feed me after midnight", "statuses_count": 140177, "id": 300701745}, "chavalina": {"lang": "en", "favourites_count": 457, "name": "chavalina", "friends_count": 117, "gender": "undetermined", "followers_count": 703, "location": "Murcia, Spain", "statuses_count": 7560, "id": 10262172}, "GDGSalamanca": {"lang": "es", "favourites_count": 303, "name": "GDG Salamanca", "friends_count": 313, "gender": "undetermined", "followers_count": 403, "location": "Salamanca, ES", "statuses_count": 741, "id": 2410875799}, "Marielme": {"lang": "es", "favourites_count": 932, "name": "Mariel Martinez", "friends_count": 322, "gender": "female", "followers_count": 229, "location": "", "statuses_count": 394, "id": 40967565}, "generoenaccion": {"lang": "es", "favourites_count": 29619, "name": "Especialista.EVEFem", "friends_count": 7298, "gender": "undetermined", "followers_count": 13150, "location": "M\u00e9xico y Espa\u00f1a", "statuses_count": 87911, "id": 208880277}, "foroatletismo": {"lang": "es", "favourites_count": 4143, "name": "Foroatletismo.com", "friends_count": 1614, "gender": "undetermined", "followers_count": 68773, "location": "Espa\u00f1a", "statuses_count": 20457, "id": 68250106}, "alistapart": {"lang": "en", "favourites_count": 568, "name": "A List Apart", "friends_count": 210, "gender": "undetermined", "followers_count": 145779, "location": "The Interwebs", "statuses_count": 2762, "id": 18776131}, "EncarniHinojosa": {"lang": "es", "favourites_count": 84, "name": "Nani  \u30ca\u30cb", "friends_count": 400, "gender": "female", "followers_count": 349, "location": "M\u00e1laga, Espa\u00f1a", "statuses_count": 3913, "id": 95928466}, "female_rate": "29%", "mhghul": {"lang": "es", "favourites_count": 2, "name": "Mohamed Hassan Algou", "friends_count": 12, "gender": "male", "followers_count": 5, "location": "", "statuses_count": 5, "id": 793102307860897792}, "karesti": {"lang": "fr", "favourites_count": 1269, "name": "Katia Aresti", "friends_count": 552, "gender": "female", "followers_count": 1547, "location": "Paris", "statuses_count": 2409, "id": 134497728}, "juliazeebee": {"lang": "en", "favourites_count": 92, "name": "Julia Byron", "friends_count": 123, "gender": "female", "followers_count": 166, "location": "", "statuses_count": 61, "id": 4277486841}, "SarahCAndersen": {"lang": "en", "favourites_count": 4624, "name": "Sarah Andersen", "friends_count": 579, "gender": "female", "followers_count": 286748, "location": "", "statuses_count": 1086, "id": 916031611}, "camaraabierta": {"lang": "en", "favourites_count": 908, "name": "C\u00e1mara abierta 2.0", "friends_count": 655, "gender": "undetermined", "followers_count": 19802, "location": "TVE", "statuses_count": 2321, "id": 52823380}, "lalalalia": {"lang": "es", "favourites_count": 19056, "name": "Anal\u00eda Plaza", "friends_count": 548, "gender": "female", "followers_count": 4661, "location": "South of the river, London", "statuses_count": 33582, "id": 15943605}, "martinidemar": {"lang": "es", "favourites_count": 8273, "name": "Berta G. de Vega", "friends_count": 2001, "gender": "female", "followers_count": 7891, "location": "Malaga", "statuses_count": 119579, "id": 224965117}, "ajplus": {"lang": "en", "favourites_count": 2033, "name": "AJ+", "friends_count": 331, "gender": "undetermined", "followers_count": 550880, "location": "", "statuses_count": 42281, "id": 110396781}, "victoriacabrera": {"lang": "es", "favourites_count": 2747, "name": "Victoria Cabrera", "friends_count": 5000, "gender": "female", "followers_count": 4477, "location": "Sevilla. Andalucia.Espa\u00f1a", "statuses_count": 9832, "id": 21649421}, "jmspool": {"lang": "en", "favourites_count": 982, "name": "Jared Spool", "friends_count": 1124, "gender": "male", "followers_count": 76662, "location": "42.635976,-71.164046", "statuses_count": 64407, "id": 849101}, "sserafinelli": {"lang": "es", "favourites_count": 143, "name": "Stefano Serafinelli", "friends_count": 394, "gender": "male", "followers_count": 355, "location": "Madrid", "statuses_count": 374, "id": 496817364}, "malaga_python": {"lang": "es", "favourites_count": 27, "name": "M\u00e1laga Python", "friends_count": 37, "gender": "undetermined", "followers_count": 220, "location": "M\u00e1laga, Espa\u00f1a", "statuses_count": 226, "id": 759715052626685952}, "MrMongillo": {"lang": "en", "favourites_count": 471, "name": "mr mongillo", "friends_count": 115, "gender": "undetermined", "followers_count": 199, "location": "Middlefield, CT", "statuses_count": 849, "id": 587635558}, "total_count": 200, "AngMartina": {"lang": "es", "favourites_count": 491, "name": "\u00c1ngela Padr\u00f3n", "friends_count": 600, "gender": "female", "followers_count": 464, "location": "", "statuses_count": 5867, "id": 214191237}, "josellinares": {"lang": "es", "favourites_count": 274, "name": "Jose Llinares", "friends_count": 663, "gender": "male", "followers_count": 5889, "location": "Madrid", "statuses_count": 4702, "id": 11067372}, "AdaLab_Digital": {"lang": "es", "favourites_count": 1324, "name": "AdaLab", "friends_count": 567, "gender": "undetermined", "followers_count": 956, "location": "Madrid, Comunidad de Madrid", "statuses_count": 1048, "id": 761153947990097920}, "orbitalaika_tve": {"lang": "es", "favourites_count": 4329, "name": "\u00d3rbita Laika", "friends_count": 215, "gender": "undetermined", "followers_count": 52536, "location": "En \u00f3rbita", "statuses_count": 7064, "id": 2892001877}, "nosequecenar": {"lang": "es", "favourites_count": 348, "name": "Julia Jim\u00e9nez", "friends_count": 84, "gender": "female", "followers_count": 533, "location": "Madrid, Comunidad de Madrid", "statuses_count": 430, "id": 843760359718748160}, "MOSMAMalaga": {"lang": "es", "favourites_count": 379, "name": "MOSMA", "friends_count": 323, "gender": "undetermined", "followers_count": 449, "location": "M\u00e1laga, Andaluc\u00eda", "statuses_count": 654, "id": 4824798461}, "RLadiesMAD": {"lang": "en", "favourites_count": 202, "name": "R-Ladies Madrid", "friends_count": 320, "gender": "undetermined", "followers_count": 466, "location": "Madrid, Spain", "statuses_count": 755, "id": 772203134269652992}, "linkbyuma": {"lang": "es", "favourites_count": 2132, "name": "LINK by UMA-ATech", "friends_count": 1178, "gender": "undetermined", "followers_count": 2221, "location": "Avenida Louis Pasteur,47 ", "statuses_count": 2778, "id": 2982583924}, "lamarea_com": {"lang": "es", "favourites_count": 10544, "name": "La Marea", "friends_count": 1184, "gender": "undetermined", "followers_count": 149999, "location": "Espa\u00f1a", "statuses_count": 33311, "id": 525416576}, "lisacrost": {"lang": "en", "favourites_count": 7915, "name": "Lisa Charlotte Rost", "friends_count": 817, "gender": "female", "followers_count": 5257, "location": "Berlin", "statuses_count": 2415, "id": 52853730}, "WekanApp": {"lang": "fr", "favourites_count": 11, "name": "Wekan", "friends_count": 13, "gender": "undetermined", "followers_count": 496, "location": "", "statuses_count": 36, "id": 3570594976}, "dotnetmalaga": {"lang": "es", "favourites_count": 154, "name": "dotnetMALAGA", "friends_count": 33, "gender": "undetermined", "followers_count": 314, "location": "M\u00e1laga, Andaluc\u00eda, Espa\u00f1a", "statuses_count": 635, "id": 3165295703}, "nikkigarcia_es": {"lang": "en", "favourites_count": 6177, "name": "Nikki Garc\u00eda", "friends_count": 576, "gender": "female", "followers_count": 5078, "location": "Madrid", "statuses_count": 8772, "id": 90303308}, "GemaiSanchez": {"lang": "es", "favourites_count": 687, "name": "Gema Isabel S\u00e1nchez", "friends_count": 2085, "gender": "female", "followers_count": 1753, "location": "M\u00e1laga", "statuses_count": 1712, "id": 113334821}, "nabaroa": {"lang": "es", "favourites_count": 3515, "name": "Naiara Abaroa", "friends_count": 295, "gender": "undetermined", "followers_count": 3222, "location": "Lekitto", "statuses_count": 11241, "id": 423563078}, "MichelleGlauser": {"lang": "en", "favourites_count": 6373, "name": "Michelle Glauser", "friends_count": 5348, "gender": "female", "followers_count": 4861, "location": "San Francisco, CA", "statuses_count": 6374, "id": 236305811}, "PoloDigitalMLG": {"lang": "es", "favourites_count": 882, "name": "Polo Digital M\u00e1laga", "friends_count": 651, "gender": "male", "followers_count": 859, "location": "M\u00e1laga, Andaluc\u00eda", "statuses_count": 1180, "id": 781829562858663936}, "nonbinary_rate": "0%", "BcnGeekGirls": {"lang": "es", "favourites_count": 8, "name": "BcnGeekGirls", "friends_count": 45, "gender": "undetermined", "followers_count": 90, "location": "Barcelona", "statuses_count": 114, "id": 2648110844}, "yamila_moreno": {"lang": "es", "favourites_count": 6892, "name": "write-only yami", "friends_count": 874, "gender": "undetermined", "followers_count": 1338, "location": "write-only account - Kaleidos", "statuses_count": 16427, "id": 153914189}, "MiraLak": {"lang": "fr", "favourites_count": 980, "name": "Amira LAKHAL", "friends_count": 518, "gender": "female", "followers_count": 2150, "location": "Lausanne, Suisse", "statuses_count": 1761, "id": 164019927}, "Betinaserrano": {"lang": "en", "favourites_count": 33132, "name": "Bananas Serrano", "friends_count": 353, "gender": "undetermined", "followers_count": 8513, "location": "Madrid", "statuses_count": 43831, "id": 33915658}, "jcmartinezma": {"lang": "es", "favourites_count": 418, "name": "JC Mart\u00ednez", "friends_count": 182, "gender": "undetermined", "followers_count": 95, "location": "M\u00e1laga", "statuses_count": 1609, "id": 157080120}, "sailormercury91": {"lang": "es", "favourites_count": 1526, "name": "Nerea Luis", "friends_count": 910, "gender": "female", "followers_count": 743, "location": "Madrid", "statuses_count": 3937, "id": 82172798}, "ubuntudesigners": {"lang": "en", "favourites_count": 66, "name": "Ubuntu Designers", "friends_count": 67, "gender": "undetermined", "followers_count": 26182, "location": "London, UK", "statuses_count": 740, "id": 45840709}, "Laura_Morillo": {"lang": "es", "favourites_count": 443, "name": "Laura Morillo", "friends_count": 359, "gender": "female", "followers_count": 1398, "location": "Madrid", "statuses_count": 3587, "id": 85189725}, "cristinafsanz": {"lang": "es", "favourites_count": 15180, "name": "Cristina Fern\u00e1ndez", "friends_count": 3751, "gender": "female", "followers_count": 1800, "location": "Madrid, Spain", "statuses_count": 5957, "id": 1067986608}, "IgualdadURJC": {"lang": "es", "favourites_count": 228, "name": "Igualdad URJC", "friends_count": 1174, "gender": "undetermined", "followers_count": 2908, "location": "observatorio.igualdad@urjc.es", "statuses_count": 3892, "id": 2987275660}, "OKInfografia": {"lang": "es", "favourites_count": 3499, "name": "Carolina Jim\u00e9nez G.", "friends_count": 1364, "gender": "female", "followers_count": 4292, "location": "Vancouver, British Columbia", "statuses_count": 5254, "id": 99961556}, "yarasenger": {"lang": "pt", "favourites_count": 3934, "name": "Yara M H Senger", "friends_count": 844, "gender": "female", "followers_count": 6044, "location": "Brasil", "statuses_count": 11990, "id": 15172295}, "pabini": {"lang": "en", "favourites_count": 27, "name": "pabini", "friends_count": 139, "gender": "undetermined", "followers_count": 263, "location": "Silicon Valley", "statuses_count": 133, "id": 18782381}, "vromer0": {"lang": "es", "favourites_count": 553, "name": "Victor Romero", "friends_count": 164, "gender": "male", "followers_count": 362, "location": "San Francisco, CA", "statuses_count": 1406, "id": 3412031}, "centroaleris": {"lang": "es", "favourites_count": 478, "name": "Centro Aleris", "friends_count": 181, "gender": "undetermined", "followers_count": 2802, "location": "Madrid, Comunidad de Madrid", "statuses_count": 1477, "id": 4830638777}, "aleyda": {"lang": "en", "favourites_count": 111, "name": "Aleyda Sol\u00eds", "friends_count": 699, "gender": "undetermined", "followers_count": 44905, "location": "Spain & often on a \u2708\ufe0f", "statuses_count": 75103, "id": 635383}, "mortizs": {"lang": "es", "favourites_count": 2368, "name": "mar\u00eda ortiz s\u00e1nchez", "friends_count": 1205, "gender": "mostly_female", "followers_count": 978, "location": "M\u00e1laga", "statuses_count": 4180, "id": 90969456}, "HETradio3": {"lang": "es", "favourites_count": 7339, "name": "Hoy empieza todo", "friends_count": 222, "gender": "undetermined", "followers_count": 32854, "location": "", "statuses_count": 8252, "id": 799792832}, "lemoncoders": {"lang": "es", "favourites_count": 405, "name": "lemoncode", "friends_count": 36, "gender": "undetermined", "followers_count": 478, "location": "", "statuses_count": 1030, "id": 1334432233}, "felizgsanchez": {"lang": "es", "favourites_count": 704, "name": "felicidadgsanchez", "friends_count": 709, "gender": "undetermined", "followers_count": 239, "location": "", "statuses_count": 1329, "id": 285272604}, "MolaSaber": {"lang": "es", "favourites_count": 4360, "name": "Mola Saber", "friends_count": 767, "gender": "undetermined", "followers_count": 12744, "location": "Las Palmas de Gran Canaria", "statuses_count": 5632, "id": 225400632}, "Snowden": {"lang": "en", "favourites_count": 0, "name": "Edward Snowden", "friends_count": 1, "gender": "male", "followers_count": 3083704, "location": "", "statuses_count": 2022, "id": 2916305152}, "yalvareztv": {"lang": "es", "favourites_count": 5405, "name": "Yolanda \u00c1lvarez", "friends_count": 746, "gender": "female", "followers_count": 20921, "location": "Madrid, Comunidad de Madrid", "statuses_count": 9932, "id": 301928168}, "stefpos": {"lang": "en", "favourites_count": 4918, "name": "Stefanie Posavec", "friends_count": 1851, "gender": "female", "followers_count": 9115, "location": "(South) London-centric", "statuses_count": 7188, "id": 15339875}, "andresrm88": {"lang": "es", "favourites_count": 118, "name": "Andr\u00e9s", "friends_count": 165, "gender": "male", "followers_count": 98, "location": "Almer\u00eda", "statuses_count": 181, "id": 231087163}, "ibdknox": {"lang": "en", "favourites_count": 444, "name": "Chris Granger", "friends_count": 31, "gender": "mostly_male", "followers_count": 8599, "location": "San Francisco", "statuses_count": 2295, "id": 189045861}, "male_count": 39, "datadista": {"lang": "en", "favourites_count": 786, "name": "Datadista", "friends_count": 62, "gender": "undetermined", "followers_count": 4535, "location": "Madrid", "statuses_count": 640, "id": 2877732249}, "merrigo_": {"lang": "en", "favourites_count": 6868, "name": "Amanda", "friends_count": 149, "gender": "female", "followers_count": 8867, "location": "Los Angeles \u2022 DTLA", "statuses_count": 5348, "id": 834290305}, "tuitocracia": {"lang": "es", "favourites_count": 1067, "name": "T-cracia", "friends_count": 1147, "gender": "undetermined", "followers_count": 6490, "location": "Espa\u00f1a", "statuses_count": 3030, "id": 2651380620}, "bolanosdecano": {"lang": "es", "favourites_count": 41, "name": "Jorge Bola\u00f1os", "friends_count": 845, "gender": "male", "followers_count": 698, "location": "Granada (Espa\u00f1a)", "statuses_count": 666, "id": 3089593384}, "Mrs_DarkDonado": {"lang": "es", "favourites_count": 28452, "name": "Marta G\u00f3mez", "friends_count": 588, "gender": "female", "followers_count": 855, "location": "Granada", "statuses_count": 35657, "id": 182307309}, "female_count": 59, "timoreilly": {"lang": "en", "favourites_count": 3068, "name": "Tim O'Reilly", "friends_count": 1699, "gender": "male", "followers_count": 1984877, "location": "Oakland, CA", "statuses_count": 41401, "id": 2384071}, "RaquelLanseros": {"lang": "es", "favourites_count": 14080, "name": "Raquel Lanseros", "friends_count": 1697, "gender": "female", "followers_count": 6181, "location": "", "statuses_count": 8986, "id": 288750771}, "rhein_wein": {"lang": "en", "favourites_count": 2446, "name": "Laura Frank", "friends_count": 559, "gender": "female", "followers_count": 4343, "location": "Berlin", "statuses_count": 4426, "id": 166583984}, "selbora": {"lang": "es", "favourites_count": 122, "name": "Ascen Robles", "friends_count": 921, "gender": "undetermined", "followers_count": 328, "location": "Ja\u00e9n / Espa\u00f1a", "statuses_count": 191, "id": 263567971}, "TodasGamers": {"lang": "es", "favourites_count": 32196, "name": "TodasGamers", "friends_count": 552, "gender": "undetermined", "followers_count": 8677, "location": "frente a la pantalla. ", "statuses_count": 48722, "id": 716694741870632960}, "laurapuertoa": {"lang": "es", "favourites_count": 114, "name": "Laura Puerto", "friends_count": 575, "gender": "female", "followers_count": 205, "location": "", "statuses_count": 295, "id": 368858406}, "sarah_edo": {"lang": "en", "favourites_count": 51985, "name": "Sarah Drasner", "friends_count": 1460, "gender": "female", "followers_count": 28294, "location": "", "statuses_count": 20689, "id": 813333008}, "MathiasLeroy_": {"lang": "fr", "favourites_count": 45, "name": "Mathias Leroy", "friends_count": 4437, "gender": "male", "followers_count": 9152, "location": "Brussels", "statuses_count": 527, "id": 477545769}, "NASA": {"lang": "en", "favourites_count": 2471, "name": "NASA", "friends_count": 263, "gender": "undetermined", "followers_count": 23391887, "location": "", "statuses_count": 46952, "id": 11348282}, "airun72": {"lang": "en", "favourites_count": 2854, "name": "Nuria Rodr\u00edguez", "friends_count": 524, "gender": "female", "followers_count": 724, "location": "M\u00e1laga, Spain.", "statuses_count": 1568, "id": 74683881}, "DikraViajes": {"lang": "es", "favourites_count": 0, "name": "Dikra Viajes", "friends_count": 19, "gender": "undetermined", "followers_count": 16, "location": "Granada, Espa\u00f1a", "statuses_count": 306, "id": 824566509586575361}, "theeremita": {"lang": "es", "favourites_count": 1766, "name": "Carmen Rosas", "friends_count": 497, "gender": "female", "followers_count": 281, "location": "", "statuses_count": 2362, "id": 390927564}, "MommyBingski": {"lang": "en", "favourites_count": 11, "name": "Bing Guevara", "friends_count": 108, "gender": "undetermined", "followers_count": 141, "location": "", "statuses_count": 428, "id": 1378509756}, "veen": {"lang": "en", "favourites_count": 6088, "name": "Jeffrey Veen", "friends_count": 674, "gender": "male", "followers_count": 42219, "location": "London", "statuses_count": 2682, "id": 414}, "unintendedbear": {"lang": "es", "favourites_count": 5313, "name": "Paloma de las Cuevas", "friends_count": 582, "gender": "female", "followers_count": 631, "location": "Granada", "statuses_count": 23445, "id": 300195350}, "bjacobo": {"lang": "es", "favourites_count": 280, "name": "Jacobo M\u00e1rquez", "friends_count": 474, "gender": "male", "followers_count": 469, "location": "Malaga & Estepona", "statuses_count": 10098, "id": 9926222}, "hydrosound": {"lang": "es", "favourites_count": 2012, "name": "Mario Martin", "friends_count": 2997, "gender": "male", "followers_count": 2136, "location": "Madrid", "statuses_count": 19292, "id": 14291568}, "Vizzuality": {"lang": "en", "favourites_count": 624, "name": "Vizzuality", "friends_count": 1799, "gender": "undetermined", "followers_count": 4600, "location": "Madrid/Cambridge/Washington DC", "statuses_count": 1768, "id": 42936497}, "ruthdefrutos": {"lang": "es", "favourites_count": 2884, "name": "ruthdefrutos", "friends_count": 1514, "gender": "undetermined", "followers_count": 1302, "location": "M\u00e1laga, Espa\u00f1a", "statuses_count": 3239, "id": 1106241937}, "Terceranexus6": {"lang": "en", "favourites_count": 11067, "name": "Nexus-\u9752\u3044\u30d3\u30fc\u30e0", "friends_count": 1280, "gender": "undetermined", "followers_count": 770, "location": "Espa\u00f1a ", "statuses_count": 16442, "id": 102027912}, "_musicalnote": {"lang": "es", "favourites_count": 4089, "name": "Cristina HG", "friends_count": 376, "gender": "female", "followers_count": 454, "location": "In the milky way", "statuses_count": 14281, "id": 1004279869}, "ideasfactory_es": {"lang": "es", "favourites_count": 654, "name": "Ideas Factory", "friends_count": 810, "gender": "undetermined", "followers_count": 1231, "location": "M\u00e1laga", "statuses_count": 1847, "id": 3148542527}, "paolaguimerans": {"lang": "en", "favourites_count": 2152, "name": "paola guimerans", "friends_count": 864, "gender": "female", "followers_count": 815, "location": "San Sebasti\u00e1n", "statuses_count": 3222, "id": 3088796211}, "undefined_rate": "47%", "usenextjournal": {"lang": "en", "favourites_count": 4, "name": "nextjournal", "friends_count": 0, "gender": "undetermined", "followers_count": 131, "location": "Berlin", "statuses_count": 31, "id": 723239888854892544}, "ddjournalism": {"lang": "en", "favourites_count": 94, "name": "DataDrivenJournalism", "friends_count": 1054, "gender": "undetermined", "followers_count": 23377, "location": "", "statuses_count": 3544, "id": 303687748}, "ana_datagirl": {"lang": "en", "favourites_count": 623, "name": "Ana Jim\u00e9nez", "friends_count": 458, "gender": "female", "followers_count": 429, "location": "", "statuses_count": 598, "id": 414723239}, "AmigosIng": {"lang": "es", "favourites_count": 10579, "name": "Amigos Ingenier\u00eda", "friends_count": 20934, "gender": "undetermined", "followers_count": 28630, "location": "Espa\u00f1a", "statuses_count": 30038, "id": 1363786782}, "GIRLposts": {"lang": "en", "favourites_count": 78572, "name": "Common White Girl", "friends_count": 144844, "gender": "undetermined", "followers_count": 7334381, "location": "", "statuses_count": 68071, "id": 132774626}, "codemotion_es": {"lang": "es", "favourites_count": 529, "name": "Codemotion Madrid", "friends_count": 158, "gender": "undetermined", "followers_count": 5929, "location": "Madrid", "statuses_count": 1969, "id": 388884371}, "mujeresenred": {"lang": "es", "favourites_count": 23, "name": "Mujeres en Red", "friends_count": 555, "gender": "undetermined", "followers_count": 24345, "location": "Planeta Tierra", "statuses_count": 1408, "id": 17647946}, "SkillSeekersAU": {"lang": "en", "favourites_count": 9, "name": "Hanna Karlsson", "friends_count": 48, "gender": "female", "followers_count": 42, "location": "", "statuses_count": 83, "id": 706994283937566720}, "enreda": {"lang": "es", "favourites_count": 467, "name": "ENREDA Cooperativa", "friends_count": 818, "gender": "undetermined", "followers_count": 1618, "location": "El Mundo ", "statuses_count": 3593, "id": 166077279}, "medlbd": {"lang": "fr", "favourites_count": 7, "name": "Mo Labadi \u0645\u062d\u0645\u062f \u0644\u0628\u0627\u062f\u064a", "friends_count": 2051, "gender": "mostly_male", "followers_count": 332, "location": "Earth (now), Mars/Moon (1 day)", "statuses_count": 1105, "id": 622295749}, "micromachismos": {"lang": "es", "favourites_count": 2350, "name": "Micromachismos", "friends_count": 106, "gender": "undetermined", "followers_count": 29667, "location": "", "statuses_count": 1361, "id": 1585968080}, "MomandGeekcom": {"lang": "es", "favourites_count": 1242, "name": "Remedios Fern\u00e1ndez", "friends_count": 472, "gender": "female", "followers_count": 391, "location": "Almer\u00eda, Espa\u00f1a", "statuses_count": 742, "id": 3080209305}, "ArcoIrisMalaga": {"lang": "es", "favourites_count": 60, "name": "Arco Iris M\u00e1laga", "friends_count": 434, "gender": "male", "followers_count": 563, "location": "M\u00e1laga, Spain", "statuses_count": 285, "id": 1465078814}, "_amatellanes": {"lang": "en", "favourites_count": 32, "name": "Adri\u00e1n Matellanes", "friends_count": 12, "gender": "male", "followers_count": 52, "location": "", "statuses_count": 62, "id": 764388939268579328}, "giorgialupi": {"lang": "en", "favourites_count": 10887, "name": "Giorgia Lupi", "friends_count": 2612, "gender": "female", "followers_count": 12274, "location": "Brooklyn", "statuses_count": 6413, "id": 38254620}, "lays147": {"lang": "en", "favourites_count": 3015, "name": "Lady Maker", "friends_count": 348, "gender": "undetermined", "followers_count": 394, "location": "Niter\u00f3i, Brasil", "statuses_count": 1919, "id": 3011090296}, "ladynightmare_2": {"lang": "en", "favourites_count": 184, "name": "Cristina", "friends_count": 156, "gender": "female", "followers_count": 126, "location": "", "statuses_count": 644, "id": 706098229360926721}, "javiermoral": {"lang": "es", "favourites_count": 646, "name": "Javier Moral", "friends_count": 874, "gender": "mostly_male", "followers_count": 1511, "location": "M\u00e1laga", "statuses_count": 3564, "id": 17535170}, "lady_nerd": {"lang": "en", "favourites_count": 3408, "name": "Laura Bell", "friends_count": 532, "gender": "female", "followers_count": 4735, "location": "Auckland,NZ", "statuses_count": 5803, "id": 125071102}, "ireneau": {"lang": "en", "favourites_count": 1623, "name": "Irene Au", "friends_count": 1503, "gender": "female", "followers_count": 16434, "location": "United States", "statuses_count": 3196, "id": 860281}, "AzaharaKahlo": {"lang": "es", "favourites_count": 1520, "name": "Azahara", "friends_count": 839, "gender": "undetermined", "followers_count": 378, "location": "Madrid", "statuses_count": 6153, "id": 341436545}, "andalucialab": {"lang": "es", "favourites_count": 803, "name": "Innovaci\u00f3n y Turismo", "friends_count": 2481, "gender": "undetermined", "followers_count": 24344, "location": "Andaluc\u00eda. Espa\u00f1a", "statuses_count": 11388, "id": 80128568}, "cienciadirecta": {"lang": "es", "favourites_count": 1845, "name": "Fundaci\u00f3n Descubre", "friends_count": 957, "gender": "undetermined", "followers_count": 7861, "location": "Andaluc\u00eda, Espa\u00f1a", "statuses_count": 12460, "id": 17233135}, "SaysHummingbird": {"lang": "en", "favourites_count": 4705, "name": "The Hummingbird", "friends_count": 36129, "gender": "mostly_female", "followers_count": 54243, "location": "", "statuses_count": 2827, "id": 810619093749559296}, "Ethelmonster": {"lang": "en", "favourites_count": 1043, "name": "Figginsworth", "friends_count": 413, "gender": "undetermined", "followers_count": 1170, "location": "", "statuses_count": 56393, "id": 2786260457}, "MarioPadilla91": {"lang": "es", "favourites_count": 139, "name": "Mario Padilla", "friends_count": 136, "gender": "male", "followers_count": 145, "location": "M\u00e1laga, Spain", "statuses_count": 168, "id": 1735584181}, "amandalinden": {"lang": "en", "favourites_count": 166, "name": "Amanda Linden", "friends_count": 286, "gender": "female", "followers_count": 979, "location": "San Carlos, CA", "statuses_count": 99, "id": 4090871}, "poornima": {"lang": "en", "favourites_count": 7458, "name": "poornima", "friends_count": 33622, "gender": "undetermined", "followers_count": 42884, "location": "Palo Alto, CA", "statuses_count": 25247, "id": 9078772}, "campanilla": {"lang": "es", "favourites_count": 2788, "name": "Campanilla", "friends_count": 462, "gender": "undetermined", "followers_count": 504, "location": "", "statuses_count": 10654, "id": 6476132}, "carmenansio": {"lang": "es", "favourites_count": 1791, "name": "carmenansio", "friends_count": 358, "gender": "undetermined", "followers_count": 292, "location": "Barcelona, Espa\u00f1a", "statuses_count": 949, "id": 556708229}, "FabLab_Malaga": {"lang": "es", "favourites_count": 132, "name": "FabLab M\u00e1laga", "friends_count": 454, "gender": "undetermined", "followers_count": 342, "location": "", "statuses_count": 142, "id": 4784261003}, "olea": {"lang": "es", "favourites_count": 13843, "name": "Ismael Olea", "friends_count": 510, "gender": "male", "followers_count": 1577, "location": "Almer\u00eda", "statuses_count": 35912, "id": 2170361}, "juliamateodc": {"lang": "fr", "favourites_count": 192, "name": "Julia Mateo", "friends_count": 387, "gender": "female", "followers_count": 375, "location": "Gen\u00e8ve, Suisse", "statuses_count": 167, "id": 215783369}, "nonbinary_count": 0, "_juancb": {"lang": "es", "favourites_count": 1220, "name": "Juan Cruz-Benito", "friends_count": 400, "gender": "male", "followers_count": 414, "location": "", "statuses_count": 2442, "id": 261658198}, "gifdata": {"lang": "es", "favourites_count": 542, "name": "V\u00edctor M. Garc\u00eda", "friends_count": 777, "gender": "male", "followers_count": 322, "location": "Benalm\u00e1dena ", "statuses_count": 5115, "id": 574943316}, "maryu_es": {"lang": "es", "favourites_count": 56, "name": "Maryu", "friends_count": 58, "gender": "undetermined", "followers_count": 38, "location": "", "statuses_count": 186, "id": 1359093870}, "palestinalibre": {"lang": "es", "favourites_count": 4476, "name": "Palestinalibre.org", "friends_count": 632, "gender": "undetermined", "followers_count": 28198, "location": "", "statuses_count": 35079, "id": 61356444}, "ModelViewMedia": {"lang": "en", "favourites_count": 672, "name": "Model View Culture", "friends_count": 245, "gender": "undetermined", "followers_count": 15110, "location": "San Francisco, CA", "statuses_count": 3046, "id": 2262399740}, "irubiobaeza": {"lang": "es", "favourites_count": 5341, "name": "Ire!", "friends_count": 602, "gender": "undetermined", "followers_count": 1497, "location": "Madrid", "statuses_count": 28722, "id": 69274647}, "domesticstream": {"lang": "es", "favourites_count": 513, "name": "Data Streamers", "friends_count": 1502, "gender": "undetermined", "followers_count": 1651, "location": "Barcelona", "statuses_count": 489, "id": 2459697654}, "Be_Sando": {"lang": "es", "favourites_count": 34, "name": "Bel\u00e9n Sandoval", "friends_count": 33, "gender": "female", "followers_count": 79, "location": "Madrid, Espa\u00f1a", "statuses_count": 28, "id": 318953341}, "danacervantes_": {"lang": "en", "favourites_count": 798, "name": "Dana Cervantes", "friends_count": 758, "gender": "female", "followers_count": 1368, "location": "M\u00e1laga", "statuses_count": 1713, "id": 602211508}, "lafabricasocial": {"lang": "es", "favourites_count": 40, "name": "La F\u00e1brica Social", "friends_count": 382, "gender": "undetermined", "followers_count": 459, "location": "M\u00e1laga", "statuses_count": 943, "id": 353347129}, "Barbijaputa": {"lang": "es", "favourites_count": 36527, "name": "Barbijaputa", "friends_count": 921, "gender": "undetermined", "followers_count": 243909, "location": "#RadFem", "statuses_count": 117275, "id": 48822802}, "joulee": {"lang": "en", "favourites_count": 2460, "name": "Julie Zhuo", "friends_count": 312, "gender": "female", "followers_count": 53130, "location": "Palo Alto, CA", "statuses_count": 2201, "id": 17611446}, "dmktmalaga": {"lang": "es", "favourites_count": 70, "name": "Digital MKT M\u00e1laga", "friends_count": 73, "gender": "undetermined", "followers_count": 72, "location": "M\u00e1laga, Espa\u00f1a", "statuses_count": 86, "id": 817645868157435909}, "manwhohasitall": {"lang": "en", "favourites_count": 16728, "name": "manwhohasitall", "friends_count": 613, "gender": "male", "followers_count": 157113, "location": "", "statuses_count": 6289, "id": 3266848870}, "accuratstudio": {"lang": "en", "favourites_count": 686, "name": "accurat", "friends_count": 1198, "gender": "undetermined", "followers_count": 5410, "location": "Milan / New York", "statuses_count": 965, "id": 1371790790}, "MinkaNet": {"lang": "es", "favourites_count": 187, "name": "Minka", "friends_count": 363, "gender": "female", "followers_count": 151, "location": "", "statuses_count": 412, "id": 4642582469}, "saleiva": {"lang": "en", "favourites_count": 1111, "name": "saleiva", "friends_count": 743, "gender": "undetermined", "followers_count": 6216, "location": "MAD & NYC", "statuses_count": 15947, "id": 29412160}, "javiercerezo": {"lang": "es", "favourites_count": 991, "name": "Javier Cerezo", "friends_count": 1262, "gender": "mostly_male", "followers_count": 4583, "location": "M\u00e1laga, Espa\u00f1a", "statuses_count": 7520, "id": 6714762}, "RemediosZafra": {"lang": "es", "favourites_count": 172, "name": "Remedios Zafra", "friends_count": 161, "gender": "female", "followers_count": 641, "location": "", "statuses_count": 174, "id": 4110594934}, "julsivo": {"lang": "en", "favourites_count": 216, "name": "J\u00falia", "friends_count": 366, "gender": "female", "followers_count": 314, "location": "Manchester, England", "statuses_count": 870, "id": 847775022}, "UNRWA_spain": {"lang": "es", "favourites_count": 6862, "name": "UNRWA Espa\u00f1a", "friends_count": 1054, "gender": "undetermined", "followers_count": 13790, "location": "Madrid", "statuses_count": 11702, "id": 56658909}, "Antiestudio": {"lang": "es", "favourites_count": 6059, "name": "Antiestudio", "friends_count": 510, "gender": "undetermined", "followers_count": 664, "location": "Zaragoza", "statuses_count": 3717, "id": 762535286}, "CuteEmergency": {"lang": "en", "favourites_count": 2767, "name": "Cute Emergency", "friends_count": 32, "gender": "undetermined", "followers_count": 4485184, "location": "", "statuses_count": 42243, "id": 568825492}, "GDGLaRioja": {"lang": "es", "favourites_count": 311, "name": "GDG La Rioja", "friends_count": 75, "gender": "undetermined", "followers_count": 190, "location": "La Rioja", "statuses_count": 1177, "id": 1625516300}, "juana_gallego": {"lang": "es", "favourites_count": 23, "name": "Juana Gallego Ayala", "friends_count": 51, "gender": "female", "followers_count": 2942, "location": "Barcelona", "statuses_count": 158, "id": 1972661876}, "wecodesign": {"lang": "es", "favourites_count": 173, "name": "WeCodeSign Podcast", "friends_count": 27, "gender": "undetermined", "followers_count": 534, "location": "#Podcasting", "statuses_count": 465, "id": 706563460583260160}, "PopulateTools": {"lang": "es", "favourites_count": 30, "name": "Populate", "friends_count": 1, "gender": "undetermined", "followers_count": 631, "location": "", "statuses_count": 78, "id": 3316955423}, "javiercanada": {"lang": "es", "favourites_count": 5543, "name": "Javier Ca\u00f1ada", "friends_count": 461, "gender": "mostly_male", "followers_count": 1413, "location": "", "statuses_count": 3163, "id": 2582764214}, "swmalaga": {"lang": "es", "favourites_count": 187, "name": "StartupWeekendM\u00e1laga", "friends_count": 138, "gender": "undetermined", "followers_count": 792, "location": "M\u00e1laga, Spain", "statuses_count": 2541, "id": 2153413219}, "Midietacojea": {"lang": "es", "favourites_count": 2779, "name": "Aitor S\u00e1nchez Garc\u00eda", "friends_count": 534, "gender": "male", "followers_count": 26588, "location": "Madrid \u2708 Albacete (Spain)", "statuses_count": 17533, "id": 402120585}, "1decada10": {"lang": "es", "favourites_count": 3966, "name": "1 de cada 10", "friends_count": 919, "gender": "undetermined", "followers_count": 2345, "location": "", "statuses_count": 6106, "id": 2676817850}, "MestiriSarah": {"lang": "fr", "favourites_count": 497, "name": "Sarah Mestiri", "friends_count": 378, "gender": "female", "followers_count": 258, "location": "Tunisie", "statuses_count": 353, "id": 417005772}, "Eudaric": {"lang": "es", "favourites_count": 2175, "name": "M 2.0", "friends_count": 291, "gender": "undetermined", "followers_count": 345, "location": "Mis borderias", "statuses_count": 27092, "id": 116771556}, "Beelzenef_": {"lang": "es", "favourites_count": 5907, "name": "Elena @ \ud83c\udf03\ud83d\udcdd\ud83d\udcbb", "friends_count": 343, "gender": "female", "followers_count": 1019, "location": "M\u00e1laga", "statuses_count": 31168, "id": 302519098}, "cc0x0n": {"lang": "es", "favourites_count": 2754, "name": "I\u00f1aki Esteve", "friends_count": 513, "gender": "male", "followers_count": 86, "location": "Teenage Wasteland", "statuses_count": 2106, "id": 3375384292}, "trecedejunio": {"lang": "es", "favourites_count": 407, "name": "Sara Alvarellos", "friends_count": 2077, "gender": "female", "followers_count": 2235, "location": "ESPA\u00d1A", "statuses_count": 1742, "id": 8123772}, "terralmarket": {"lang": "es", "favourites_count": 355, "name": "Terral Market", "friends_count": 688, "gender": "undetermined", "followers_count": 396, "location": "M\u00e1laga, Andaluc\u00eda", "statuses_count": 239, "id": 730828124443844612}, "julioGarPer": {"lang": "es", "favourites_count": 23, "name": "Julio Garc\u00eda P\u00e9rez", "friends_count": 147, "gender": "male", "followers_count": 163, "location": "Huelva / Madrid", "statuses_count": 48, "id": 392072944}, "radioskylab_es": {"lang": "es", "favourites_count": 2482, "name": "Radio Skylab", "friends_count": 455, "gender": "undetermined", "followers_count": 3591, "location": "Islas Canarias, Espa\u00f1a", "statuses_count": 1106, "id": 760515512577224704}, "alqudsandalucia": {"lang": "es", "favourites_count": 672, "name": "Asociaci\u00f3n Al-Quds", "friends_count": 1143, "gender": "undetermined", "followers_count": 905, "location": "951212726", "statuses_count": 3416, "id": 1867651063}, "IgnaciodeNuevo": {"lang": "es", "favourites_count": 517, "name": "Ignacio Villanueva", "friends_count": 454, "gender": "male", "followers_count": 580, "location": "Madrid, Spain", "statuses_count": 5235, "id": 2730132444}, "undefined_count": 94, "AraRodriguezT": {"lang": "es", "favourites_count": 764, "name": "Ara Rodr\u00edguez", "friends_count": 397, "gender": "male", "followers_count": 804, "location": "Madrid, Comunidad de Madrid", "statuses_count": 1560, "id": 3332516362}, "graphext": {"lang": "es", "favourites_count": 382, "name": "graphext", "friends_count": 13, "gender": "undetermined", "followers_count": 1651, "location": "Google Campus Madrid", "statuses_count": 124, "id": 2907682397}, "MalagaViz": {"lang": "es", "favourites_count": 2, "name": "M\u00e1lagaVIZ", "friends_count": 56, "gender": "undetermined", "followers_count": 59, "location": "M\u00e1laga, Espa\u00f1a", "statuses_count": 120, "id": 758213447985364992}, "AlgouHassan": {"lang": "es", "favourites_count": 1, "name": "mohamed hassan algou", "friends_count": 7, "gender": "male", "followers_count": 4, "location": "", "statuses_count": 12, "id": 738458679079473152}, "juanmaperez85": {"lang": "es", "favourites_count": 634, "name": "Juan Manuel P\u00e9rez", "friends_count": 264, "gender": "male", "followers_count": 179, "location": "M\u00e1laga & C\u00f3rdoba", "statuses_count": 2922, "id": 237783873}, "mm_tr": {"lang": "en", "favourites_count": 530, "name": "Miguel Torres", "friends_count": 92, "gender": "male", "followers_count": 85, "location": "M\u00e1laga", "statuses_count": 1130, "id": 317378321}, "hmason": {"lang": "en", "favourites_count": 8342, "name": "Hilary Mason", "friends_count": 1413, "gender": "female", "followers_count": 90248, "location": "NYC", "statuses_count": 16425, "id": 765548}, "EmmaWatson": {"lang": "en", "favourites_count": 1010, "name": "Emma Watson", "friends_count": 353, "gender": "female", "followers_count": 24595952, "location": "", "statuses_count": 1580, "id": 166739404}, "themoviedb": {"lang": "en", "favourites_count": 60, "name": "The Movie Database", "friends_count": 5, "gender": "mostly_female", "followers_count": 7113, "location": "Calgary, Canada", "statuses_count": 1834, "id": 35701585}, "victorianoi": {"lang": "en", "favourites_count": 13354, "name": "Victoriano Izquierdo", "friends_count": 813, "gender": "male", "followers_count": 14122, "location": "In Madrid from Granada, Spain", "statuses_count": 44406, "id": 10977452}, "EburyES": {"lang": "es", "favourites_count": 31, "name": "Ebury Espa\u00f1a", "friends_count": 622, "gender": "undetermined", "followers_count": 644, "location": "Madrid", "statuses_count": 2358, "id": 552553981}, "merceduska": {"lang": "es", "favourites_count": 652, "name": "Mer", "friends_count": 122, "gender": "undetermined", "followers_count": 46, "location": "", "statuses_count": 262, "id": 237924467}, "VirginiaDiazR3": {"lang": "es", "favourites_count": 50356, "name": "Virginia D\u00edaz", "friends_count": 956, "gender": "female", "followers_count": 38341, "location": "", "statuses_count": 34575, "id": 549275299}}, "favourites_count": 5539, "name": "\u0643\u0631\u0645\u0644 \u062d\u0633\u0646", "friends_count": 854, "undefined_count": 0, "gender": "undetermined", "male_count": 97, "female_rate": "22%", "nonbinary_rate": "45%", "followers_count": 1277, "location": "Palestina granadina en M\u00e1laga", "total_count": 353, "female_count": 80, "statuses_count": 10849, "undefined_rate": "0%", "male_rate": "27%", "id": 2727511, "followers_list": {"alonsouribe": {"lang": "es", "favourites_count": 467, "name": "Alonso Uribe", "friends_count": 422, "gender": "male", "followers_count": 134, "location": "Sinaloa, M\u00e9xico", "statuses_count": 465, "id": 62300809}, "male_rate": "35%", "isaezdesign": {"lang": "es", "favourites_count": 4842, "name": "Izaskun", "friends_count": 1654, "gender": "female", "followers_count": 3767, "location": "Bilbao \u2194\ufe0f Barcelona", "statuses_count": 27887, "id": 329513767}, "AlgouHassan": {"lang": "es", "favourites_count": 1, "name": "mohamed hassan algou", "friends_count": 7, "gender": "male", "followers_count": 4, "location": "", "statuses_count": 12, "id": 738458679079473152}, "milesandagile": {"lang": "en", "favourites_count": 460, "name": "Juan P\u00e9rez", "friends_count": 406, "gender": "male", "followers_count": 2187, "location": "Spain and beyond", "statuses_count": 1157, "id": 26085565}, "BettoD": {"lang": "es", "favourites_count": 46, "name": "Alberto P\u00e9rez", "friends_count": 569, "gender": "male", "followers_count": 152, "location": "Venezuela", "statuses_count": 160, "id": 258194770}, "rephus": {"lang": "en", "favourites_count": 455, "name": "Javi Rengel", "friends_count": 268, "gender": "undetermined", "followers_count": 264, "location": "London, England", "statuses_count": 5196, "id": 13107532}, "original101": {"lang": "en", "favourites_count": 1, "name": "Nick Reid", "friends_count": 106, "gender": "male", "followers_count": 12, "location": "", "statuses_count": 1, "id": 25214195}, "fatigadacon": {"lang": "es", "favourites_count": 73, "name": "F\u00e1tima Garc\u00eda", "friends_count": 411, "gender": "female", "followers_count": 201, "location": "Spain", "statuses_count": 2012, "id": 542875821}, "RemediosZafra": {"lang": "es", "favourites_count": 172, "name": "Remedios Zafra", "friends_count": 161, "gender": "female", "followers_count": 641, "location": "", "statuses_count": 174, "id": 4110594934}, "noregretforever": {"lang": "en", "favourites_count": 245, "name": "Physiopraxis Roger Z", "friends_count": 4995, "gender": "undetermined", "followers_count": 1424, "location": "Berlin/L\u00fcdenscheid Germany", "statuses_count": 753, "id": 703149793434939392}, "JesusEnLaNet": {"lang": "es", "favourites_count": 357, "name": "Jesus Gutierrez", "friends_count": 245, "gender": "mostly_male", "followers_count": 152, "location": "Donde pisen mis pies", "statuses_count": 1514, "id": 199724491}, "elrincondpensar": {"lang": "es", "favourites_count": 3069, "name": "Esmeralda B", "friends_count": 306, "gender": "female", "followers_count": 124, "location": "", "statuses_count": 1121, "id": 253800315}, "geekandtechgirl": {"lang": "es", "favourites_count": 576, "name": "Geek & Tech Girls", "friends_count": 398, "gender": "undetermined", "followers_count": 715, "location": "Granada, Espa\u00f1a", "statuses_count": 1182, "id": 783584842277609472}, "pmolinam": {"lang": "es", "favourites_count": 2497, "name": "Pedro J. Molina", "friends_count": 1020, "gender": "male", "followers_count": 1223, "location": "Sevilla, Espa\u00f1a, EU", "statuses_count": 12729, "id": 156225514}, "Culta_y_HOT": {"lang": "es", "favourites_count": 2, "name": "Culta y ardiente", "friends_count": 51582, "gender": "undetermined", "followers_count": 52243, "location": "", "statuses_count": 76361, "id": 3130789637}, "ernestopimentel": {"lang": "en", "favourites_count": 6, "name": "Ernesto Pimentel", "friends_count": 78, "gender": "male", "followers_count": 268, "location": "M\u00e1laga", "statuses_count": 14, "id": 99142037}, "ValoFluff": {"lang": "en-gb", "favourites_count": 4, "name": "Fluffy", "friends_count": 23, "gender": "undetermined", "followers_count": 2, "location": "Everywhere and nowhere baby....", "statuses_count": 4, "id": 764781426231406592}, "Xaviju": {"lang": "es", "favourites_count": 6593, "name": "Xaviju", "friends_count": 613, "gender": "undetermined", "followers_count": 943, "location": "Madrid ~ Valencia", "statuses_count": 9005, "id": 16130258}, "ignacio2515": {"lang": "es", "favourites_count": 1, "name": "ignacio", "friends_count": 1007, "gender": "male", "followers_count": 123, "location": "Aranda de Duero, Espa\u00f1a", "statuses_count": 151, "id": 4708978349}, "poornima": {"lang": "en", "favourites_count": 7458, "name": "poornima", "friends_count": 33622, "gender": "undetermined", "followers_count": 42884, "location": "Palo Alto, CA", "statuses_count": 25247, "id": 9078772}, "sebastian_unda": {"lang": "es", "favourites_count": 56, "name": "Sebasti\u00e1n | Elastic", "friends_count": 493, "gender": "male", "followers_count": 222, "location": "Madrid", "statuses_count": 477, "id": 233479022}, "ClarisseIsidoro": {"lang": "es", "favourites_count": 57925, "name": "ClarisseBradbury", "friends_count": 3373, "gender": "undetermined", "followers_count": 3527, "location": " Don't feed me after midnight", "statuses_count": 140177, "id": 300701745}, "2895923427Vi": {"lang": "zh-cn", "favourites_count": 3863, "name": "Grace", "friends_count": 2467, "gender": "female", "followers_count": 1110, "location": "", "statuses_count": 1254, "id": 3867590053}, "reactivo": {"lang": "es", "favourites_count": 2501, "name": "reactivo", "friends_count": 1406, "gender": "undetermined", "followers_count": 434, "location": "London, England", "statuses_count": 4995, "id": 26975776}, "jdonsan": {"lang": "es", "favourites_count": 4678, "name": "Jose Dongil", "friends_count": 367, "gender": "male", "followers_count": 545, "location": "Madrid, Comunidad de Madrid", "statuses_count": 9333, "id": 251594509}, "GDGSalamanca": {"lang": "es", "favourites_count": 303, "name": "GDG Salamanca", "friends_count": 313, "gender": "undetermined", "followers_count": 403, "location": "Salamanca, ES", "statuses_count": 741, "id": 2410875799}, "guillerminacl11": {"lang": "es", "favourites_count": 131, "name": "Guillermina Claros", "friends_count": 44, "gender": "undetermined", "followers_count": 43, "location": "Rinc\u00f3n de la Victoria, Espa\u00f1a", "statuses_count": 63, "id": 729583823856533504}, "ilozano2": {"lang": "es", "favourites_count": 486, "name": "Nacho Lozano^2", "friends_count": 249, "gender": "male", "followers_count": 86, "location": "Sevilla, Espa\u00f1a", "statuses_count": 391, "id": 2495244777}, "RafaelWrites": {"lang": "en", "favourites_count": 29192, "name": "Rafael Amadeus Hines", "friends_count": 101671, "gender": "male", "followers_count": 109429, "location": "New York, NY", "statuses_count": 44896, "id": 4385421951}, "AnaMonrealC": {"lang": "es", "favourites_count": 1024, "name": "Ana Monreal", "friends_count": 775, "gender": "female", "followers_count": 732, "location": "M\u00e1laga", "statuses_count": 1161, "id": 564904596}, "female_rate": "17%", "mhghul": {"lang": "es", "favourites_count": 2, "name": "Mohamed Hassan Algou", "friends_count": 12, "gender": "male", "followers_count": 5, "location": "", "statuses_count": 5, "id": 793102307860897792}, "karesti": {"lang": "fr", "favourites_count": 1269, "name": "Katia Aresti", "friends_count": 552, "gender": "female", "followers_count": 1547, "location": "Paris", "statuses_count": 2409, "id": 134497728}, "munozdiazgerman": {"lang": "es", "favourites_count": 868, "name": "German Munoz", "friends_count": 534, "gender": "male", "followers_count": 626, "location": "Sevilla - Chicago", "statuses_count": 5932, "id": 708818065}, "supereconline": {"lang": "es", "favourites_count": 1, "name": "Super-eco", "friends_count": 1619, "gender": "undetermined", "followers_count": 219, "location": "Madrid, Comunidad de Madrid", "statuses_count": 46, "id": 791294260083556352}, "Natachi_nay": {"lang": "en-gb", "favourites_count": 411, "name": "Una Padawan", "friends_count": 810, "gender": "female", "followers_count": 293, "location": "Colombia", "statuses_count": 1930, "id": 151947616}, "MddWork": {"lang": "en", "favourites_count": 94, "name": "MDDWork", "friends_count": 61, "gender": "undetermined", "followers_count": 14, "location": "London, England", "statuses_count": 210, "id": 747772530325348352}, "MaxeiArtesanias": {"lang": "es", "favourites_count": 744, "name": "Maxei Artesan\u00edas", "friends_count": 2377, "gender": "undetermined", "followers_count": 1831, "location": "", "statuses_count": 226, "id": 3988123757}, "total_count": 200, "GausSeidel": {"lang": "es", "favourites_count": 37, "name": "Marco", "friends_count": 44, "gender": "male", "followers_count": 21, "location": "", "statuses_count": 50, "id": 245741012}, "Karmel91933867": {"lang": "id", "favourites_count": 0, "name": "Karmel", "friends_count": 97, "gender": "male", "followers_count": 0, "location": "", "statuses_count": 1, "id": 815850197657845760}, "aunderroad": {"lang": "en", "favourites_count": 8, "name": "adam", "friends_count": 4253, "gender": "male", "followers_count": 910, "location": "New York, NY", "statuses_count": 8971, "id": 15518671}, "kremaster": {"lang": "es", "favourites_count": 7199, "name": "\u00c1lvaro Varona", "friends_count": 995, "gender": "male", "followers_count": 4227, "location": "Madrid", "statuses_count": 27800, "id": 4779511}, "auladot": {"lang": "es", "favourites_count": 9, "name": "auladot", "friends_count": 272, "gender": "undetermined", "followers_count": 45, "location": "C\u00e1diz, Espa\u00f1a", "statuses_count": 0, "id": 737606560826855424}, "javisanxez": {"lang": "es", "favourites_count": 73, "name": "JaviSanchez", "friends_count": 284, "gender": "undetermined", "followers_count": 130, "location": "online", "statuses_count": 529, "id": 213590292}, "AngMartina": {"lang": "es", "favourites_count": 491, "name": "\u00c1ngela Padr\u00f3n", "friends_count": 600, "gender": "female", "followers_count": 464, "location": "", "statuses_count": 5867, "id": 214191237}, "Cristina1977CF": {"lang": "es", "favourites_count": 0, "name": "Cristina Rodr\u00edguez", "friends_count": 93, "gender": "female", "followers_count": 4, "location": "", "statuses_count": 2, "id": 779253383572185088}, "uxandalucia": {"lang": "es", "favourites_count": 109, "name": "UXMEET", "friends_count": 400, "gender": "undetermined", "followers_count": 168, "location": "Andaluc\u00eda, Espa\u00f1a", "statuses_count": 90, "id": 773337211408449536}, "pablodoble": {"lang": "es", "favourites_count": 606, "name": "Pobla", "friends_count": 383, "gender": "undetermined", "followers_count": 366, "location": "M\u00e1laga - Comarca Borz\u00f3n", "statuses_count": 12983, "id": 249186226}, "sergioestu": {"lang": "es", "favourites_count": 983, "name": "SRB", "friends_count": 943, "gender": "undetermined", "followers_count": 349, "location": "", "statuses_count": 16013, "id": 101750647}, "nonbinary_count": 0, "librosdemivida": {"lang": "es", "favourites_count": 44701, "name": "Fernando Rivera \u270d", "friends_count": 169528, "gender": "male", "followers_count": 217469, "location": "Madrid, Comunidad de Madrid", "statuses_count": 10089, "id": 2844841960}, "ferukoortiz": {"lang": "es", "favourites_count": 5159, "name": "Fernando Ortiz", "friends_count": 4963, "gender": "male", "followers_count": 431, "location": "Bogot\u00e1, D.C., Colombia", "statuses_count": 1087, "id": 767094428813099008}, "yeisonlopez_": {"lang": "es", "favourites_count": 177, "name": "Yeison L\u00f3pez", "friends_count": 737, "gender": "undetermined", "followers_count": 71, "location": "", "statuses_count": 81, "id": 539070260}, "fugii121": {"lang": "en", "favourites_count": 0, "name": "FUNII", "friends_count": 4926, "gender": "undetermined", "followers_count": 1314, "location": "", "statuses_count": 11, "id": 825520668267667456}, "EstherGalicia": {"lang": "es", "favourites_count": 2132, "name": "Esther Galicia", "friends_count": 824, "gender": "female", "followers_count": 1557, "location": "Barcelona-M\u00e1laga", "statuses_count": 8027, "id": 418942488}, "achamoman": {"lang": "es", "favourites_count": 1140, "name": "Antonio Chamorro", "friends_count": 534, "gender": "male", "followers_count": 351, "location": "", "statuses_count": 4394, "id": 193439701}, "mambanegra86": {"lang": "es", "favourites_count": 616, "name": "Alicia Garc\u00eda", "friends_count": 190, "gender": "female", "followers_count": 389, "location": "Salamanca", "statuses_count": 4269, "id": 59621538}, "Qualisys_": {"lang": "en", "favourites_count": 11, "name": "Software Empresarial", "friends_count": 2803, "gender": "undetermined", "followers_count": 1915, "location": "Pasto - Colombia ", "statuses_count": 1810, "id": 116786526}, "lukeb0nd": {"lang": "en", "favourites_count": 1939, "name": "Luke Bond", "friends_count": 819, "gender": "male", "followers_count": 840, "location": "London", "statuses_count": 1729, "id": 209328799}, "MichelleGlauser": {"lang": "en", "favourites_count": 6373, "name": "Michelle Glauser", "friends_count": 5348, "gender": "female", "followers_count": 4861, "location": "San Francisco, CA", "statuses_count": 6374, "id": 236305811}, "kaleidanet": {"lang": "en", "favourites_count": 13, "name": "Kaleida", "friends_count": 437, "gender": "undetermined", "followers_count": 155, "location": "", "statuses_count": 195, "id": 4899503848}, "xzehiox": {"lang": "es", "favourites_count": 37, "name": "Sergio Jurado", "friends_count": 290, "gender": "male", "followers_count": 99, "location": "M\u00e1laga, Spain", "statuses_count": 584, "id": 163075184}, "nonbinary_rate": "0%", "EyesDecide": {"lang": "en-gb", "favourites_count": 117, "name": "EyesDecide", "friends_count": 998, "gender": "undetermined", "followers_count": 512, "location": "Melbourne, Victoria, Australia", "statuses_count": 179, "id": 712081004987604992}, "jcmartinezma": {"lang": "es", "favourites_count": 418, "name": "JC Mart\u00ednez", "friends_count": 182, "gender": "undetermined", "followers_count": 95, "location": "M\u00e1laga", "statuses_count": 1609, "id": 157080120}, "dima_david": {"lang": "en", "favourites_count": 1532, "name": "David Ismailov", "friends_count": 1765, "gender": "male", "followers_count": 1276, "location": "Israel", "statuses_count": 1803, "id": 15520022}, "carmenansio": {"lang": "es", "favourites_count": 1791, "name": "carmenansio", "friends_count": 358, "gender": "undetermined", "followers_count": 292, "location": "Barcelona, Espa\u00f1a", "statuses_count": 949, "id": 556708229}, "juanmaperez85": {"lang": "es", "favourites_count": 634, "name": "Juan Manuel P\u00e9rez", "friends_count": 264, "gender": "male", "followers_count": 179, "location": "M\u00e1laga & C\u00f3rdoba", "statuses_count": 2922, "id": 237783873}, "SerratoGarc": {"lang": "es", "favourites_count": 8, "name": "Antonio Serrato Garc", "friends_count": 93, "gender": "male", "followers_count": 13, "location": "", "statuses_count": 0, "id": 738585753932832769}, "SparklingBenW": {"lang": "nl", "favourites_count": 1, "name": "Sparkling", "friends_count": 107, "gender": "undetermined", "followers_count": 13, "location": "Flevoweg, Leiden, Netherlands", "statuses_count": 14, "id": 2367242701}, "andredelrio": {"lang": "en", "favourites_count": 1473, "name": "Andrea Del Rio", "friends_count": 1310, "gender": "female", "followers_count": 660, "location": "Vancouver, BC, Canada", "statuses_count": 1304, "id": 43640837}, "uxbcbilbao": {"lang": "en", "favourites_count": 421, "name": "Bilbao UX Book Club", "friends_count": 348, "gender": "undetermined", "followers_count": 327, "location": "", "statuses_count": 582, "id": 128822581}, "filiramster": {"lang": "es", "favourites_count": 209, "name": "Ramiro Nvillaveiran", "friends_count": 652, "gender": "male", "followers_count": 161, "location": "", "statuses_count": 734, "id": 2689520003}, "LBascones": {"lang": "es", "favourites_count": 77, "name": "Luis Miguel Bascones", "friends_count": 352, "gender": "male", "followers_count": 361, "location": "Madrid", "statuses_count": 637, "id": 219321902}, "bolanosdecano": {"lang": "es", "favourites_count": 41, "name": "Jorge Bola\u00f1os", "friends_count": 845, "gender": "male", "followers_count": 698, "location": "Granada (Espa\u00f1a)", "statuses_count": 666, "id": 3089593384}, "hamziabouraas": {"lang": "en", "favourites_count": 88, "name": "Hamze Abou Raas", "friends_count": 179, "gender": "undetermined", "followers_count": 38, "location": "", "statuses_count": 2354, "id": 712315039147921408}, "mortizs": {"lang": "es", "favourites_count": 2368, "name": "mar\u00eda ortiz s\u00e1nchez", "friends_count": 1205, "gender": "mostly_female", "followers_count": 978, "location": "M\u00e1laga", "statuses_count": 4180, "id": 90969456}, "HacheMiryam": {"lang": "es", "favourites_count": 4129, "name": "Miryam Hache", "friends_count": 3797, "gender": "female", "followers_count": 1494, "location": "Barcelona ", "statuses_count": 2188, "id": 3244732119}, "Teixedelo": {"lang": "es", "favourites_count": 225, "name": "Teixedelo", "friends_count": 388, "gender": "undetermined", "followers_count": 178, "location": "Algorta", "statuses_count": 2280, "id": 111950021}, "Alejandrozh": {"lang": "es", "favourites_count": 200, "name": "Alejandro Zarzalejo", "friends_count": 1200, "gender": "male", "followers_count": 288, "location": "Madrid", "statuses_count": 253, "id": 70633706}, "Mrs_DarkDonado": {"lang": "es", "favourites_count": 28452, "name": "Marta G\u00f3mez", "friends_count": 588, "gender": "female", "followers_count": 855, "location": "Granada", "statuses_count": 35657, "id": 182307309}, "VelascoGomezM": {"lang": "es", "favourites_count": 695, "name": "Maria Velasco Gomez", "friends_count": 507, "gender": "mostly_female", "followers_count": 719, "location": "", "statuses_count": 610, "id": 1676273360}, "female_count": 35, "GemaiSanchez": {"lang": "es", "favourites_count": 687, "name": "Gema Isabel S\u00e1nchez", "friends_count": 2085, "gender": "female", "followers_count": 1753, "location": "M\u00e1laga", "statuses_count": 1712, "id": 113334821}, "selbora": {"lang": "es", "favourites_count": 122, "name": "Ascen Robles", "friends_count": 921, "gender": "undetermined", "followers_count": 328, "location": "Ja\u00e9n / Espa\u00f1a", "statuses_count": 191, "id": 263567971}, "cowfaceblog": {"lang": "es", "favourites_count": 3315, "name": "Algo supuestamente..", "friends_count": 130, "gender": "undetermined", "followers_count": 70, "location": "Contra el coaching y los gur\u00fas", "statuses_count": 1013, "id": 810798610782834688}, "Cricricat": {"lang": "es", "favourites_count": 1336, "name": "Du bist h\u00e4sslich", "friends_count": 2287, "gender": "undetermined", "followers_count": 137, "location": "", "statuses_count": 403, "id": 598347556}, "laurapuertoa": {"lang": "es", "favourites_count": 114, "name": "Laura Puerto", "friends_count": 575, "gender": "female", "followers_count": 205, "location": "", "statuses_count": 295, "id": 368858406}, "kathstraub": {"lang": "en", "favourites_count": 396, "name": "Kath Straub", "friends_count": 4514, "gender": "female", "followers_count": 4037, "location": "Usually Arizona or Maryland US", "statuses_count": 2908, "id": 247913}, "nobert": {"lang": "en", "favourites_count": 14765, "name": "Alex Nobert", "friends_count": 3234, "gender": "male", "followers_count": 1721, "location": "Ottawa, Ontario", "statuses_count": 32806, "id": 14861000}, "cuestademoyano": {"lang": "pt", "favourites_count": 296, "name": "Territorio Moyano", "friends_count": 891, "gender": "undetermined", "followers_count": 594, "location": "", "statuses_count": 245, "id": 723410786362650624}, "SHOPDISCOUNTSON": {"lang": "es", "favourites_count": 0, "name": "online_shopping_sale", "friends_count": 138, "gender": "undetermined", "followers_count": 4, "location": "", "statuses_count": 0, "id": 843453454492356608}, "PeterAndrewN": {"lang": "en", "favourites_count": 12, "name": "Peter", "friends_count": 898, "gender": "male", "followers_count": 17, "location": "Connecticut, USA", "statuses_count": 3, "id": 858119201852194816}, "DikraViajes": {"lang": "es", "favourites_count": 0, "name": "Dikra Viajes", "friends_count": 19, "gender": "undetermined", "followers_count": 16, "location": "Granada, Espa\u00f1a", "statuses_count": 306, "id": 824566509586575361}, "theeremita": {"lang": "es", "favourites_count": 1766, "name": "Carmen Rosas", "friends_count": 497, "gender": "female", "followers_count": 281, "location": "", "statuses_count": 2362, "id": 390927564}, "_juancb": {"lang": "es", "favourites_count": 1220, "name": "Juan Cruz-Benito", "friends_count": 400, "gender": "male", "followers_count": 414, "location": "", "statuses_count": 2442, "id": 261658198}, "CooeeDesign": {"lang": "en", "favourites_count": 33022, "name": "Cooee Design", "friends_count": 69752, "gender": "undetermined", "followers_count": 72656, "location": "Global", "statuses_count": 8559, "id": 1967291292}, "pilarccasi": {"lang": "en", "favourites_count": 9075, "name": "Pilar C. Casi", "friends_count": 789, "gender": "female", "followers_count": 894, "location": "", "statuses_count": 11438, "id": 17250130}, "EseriMORE": {"lang": "es", "favourites_count": 185, "name": "Aurelio Gallardo", "friends_count": 52, "gender": "male", "followers_count": 79, "location": "Jerez de la Frontera, Espa\u00f1a", "statuses_count": 248, "id": 1277328654}, "E21_Studios": {"lang": "es", "favourites_count": 17, "name": "E21 Studios", "friends_count": 4999, "gender": "undetermined", "followers_count": 763, "location": "Colombia", "statuses_count": 15, "id": 2359987248}, "bigdatatelco1": {"lang": "en", "favourites_count": 3, "name": "Big Data and Telco", "friends_count": 4785, "gender": "undetermined", "followers_count": 1595, "location": "United Kingdom", "statuses_count": 1005, "id": 744953241578905600}, "yavallejo": {"lang": "es", "favourites_count": 1034, "name": "yan arlex vallejo", "friends_count": 2998, "gender": "male", "followers_count": 2327, "location": "Colombia", "statuses_count": 9485, "id": 193345259}, "Uxresarchgeeks": {"lang": "en", "favourites_count": 0, "name": "Uxresearchgeeks", "friends_count": 35, "gender": "undetermined", "followers_count": 5, "location": "Malaga, Spain", "statuses_count": 4, "id": 770654368215556096}, "Terceranexus6": {"lang": "en", "favourites_count": 11067, "name": "Nexus-\u9752\u3044\u30d3\u30fc\u30e0", "friends_count": 1280, "gender": "undetermined", "followers_count": 770, "location": "Espa\u00f1a ", "statuses_count": 16442, "id": 102027912}, "Amin_chronicles": {"lang": "es", "favourites_count": 64, "name": "Amin", "friends_count": 1067, "gender": "male", "followers_count": 423, "location": "Espa\u00f1a", "statuses_count": 109, "id": 785179748414685185}, "colourwithus": {"lang": "en", "favourites_count": 1299, "name": "Colours", "friends_count": 1854, "gender": "undetermined", "followers_count": 497, "location": "Salt Lake City, UT", "statuses_count": 275, "id": 3444096372}, "hablapps": {"lang": "es", "favourites_count": 101, "name": "Habla Computing", "friends_count": 385, "gender": "undetermined", "followers_count": 234, "location": "Spain", "statuses_count": 245, "id": 460317459}, "monetelab": {"lang": "es", "favourites_count": 7, "name": "monetelab", "friends_count": 252, "gender": "undetermined", "followers_count": 21, "location": "", "statuses_count": 13, "id": 4876482767}, "undefined_rate": "41%", "ZurineAlacreu": {"lang": "es", "favourites_count": 153, "name": "Zuri\u00f1e Alacreu", "friends_count": 119, "gender": "female", "followers_count": 45, "location": "", "statuses_count": 68, "id": 2329143126}, "Anton_Devel": {"lang": "es", "favourites_count": 14, "name": "Jose Antonio Ruiz", "friends_count": 66, "gender": "male", "followers_count": 5, "location": "", "statuses_count": 19, "id": 743872178450477056}, "AmigosIng": {"lang": "es", "favourites_count": 10579, "name": "Amigos Ingenier\u00eda", "friends_count": 20934, "gender": "undetermined", "followers_count": 28630, "location": "Espa\u00f1a", "statuses_count": 30038, "id": 1363786782}, "darmng": {"lang": "ca", "favourites_count": 1276, "name": "Dani Armengol", "friends_count": 95, "gender": "male", "followers_count": 1075, "location": "Vic - Barcelona (Spain)", "statuses_count": 10263, "id": 290715597}, "transaminasa": {"lang": "es", "favourites_count": 2581, "name": "Maripepis", "friends_count": 219, "gender": "undetermined", "followers_count": 349, "location": "", "statuses_count": 11825, "id": 142271139}, "EncarniHinojosa": {"lang": "es", "favourites_count": 84, "name": "Nani  \u30ca\u30cb", "friends_count": 400, "gender": "female", "followers_count": 349, "location": "M\u00e1laga, Espa\u00f1a", "statuses_count": 3913, "id": 95928466}, "Vishal1886": {"lang": "en", "favourites_count": 578, "name": "Vishal Prajapati", "friends_count": 986, "gender": "undetermined", "followers_count": 84, "location": "Gujarat, India", "statuses_count": 519, "id": 3039767191}, "sencillabelia": {"lang": "es", "favourites_count": 1, "name": "Maria E \u2764\ufe0f\ud83d\udc9b\ud83d\udc9a\ud83d\udc99\ud83d\udc9c", "friends_count": 307, "gender": "mostly_female", "followers_count": 73, "location": "Granada, Espa\u00f1a", "statuses_count": 38, "id": 808019626730909697}, "socialpilot_co": {"lang": "en", "favourites_count": 3309, "name": "SocialPilot", "friends_count": 3303, "gender": "undetermined", "followers_count": 11253, "location": "", "statuses_count": 1595, "id": 2401885398}, "JoseAntPR": {"lang": "es", "favourites_count": 1137, "name": "Jose Antonio", "friends_count": 317, "gender": "male", "followers_count": 385, "location": "M\u00e1laga", "statuses_count": 476, "id": 381150181}, "jimenez_miguela": {"lang": "es", "favourites_count": 22, "name": "Miguel \u00c1ngel Jim\u00e9nez", "friends_count": 58, "gender": "male", "followers_count": 12, "location": "M\u00e1laga ", "statuses_count": 44, "id": 1681266631}, "medlbd": {"lang": "fr", "favourites_count": 7, "name": "Mo Labadi \u0645\u062d\u0645\u062f \u0644\u0628\u0627\u062f\u064a", "friends_count": 2051, "gender": "mostly_male", "followers_count": 332, "location": "Earth (now), Mars/Moon (1 day)", "statuses_count": 1105, "id": 622295749}, "JaviPerez1": {"lang": "es", "favourites_count": 1384, "name": "Javi P\u00e9rez", "friends_count": 1798, "gender": "undetermined", "followers_count": 1677, "location": "ATQ,TLS, SVQ, Albanta, AGP", "statuses_count": 8336, "id": 56961331}, "Mohamedtomoni20": {"lang": "ar", "favourites_count": 0, "name": "Mohamed Abdallah", "friends_count": 153, "gender": "male", "followers_count": 6, "location": "", "statuses_count": 1, "id": 819169842179649540}, "HRCS_SPAIN": {"lang": "es", "favourites_count": 243, "name": "HRCS", "friends_count": 2430, "gender": "undetermined", "followers_count": 2095, "location": "M\u00e1laga, Andaluc\u00eda", "statuses_count": 3907, "id": 97254755}, "rf_ventura": {"lang": "es", "favourites_count": 810, "name": "rafael ventura", "friends_count": 2576, "gender": "male", "followers_count": 2600, "location": "", "statuses_count": 7485, "id": 133451006}, "limitnordest": {"lang": "es", "favourites_count": 65, "name": "limitnordest", "friends_count": 208, "gender": "undetermined", "followers_count": 137, "location": "Catalunya", "statuses_count": 1691, "id": 312122196}, "LarsimontT": {"lang": "fr", "favourites_count": 79, "name": "Larsimont Thomas", "friends_count": 3777, "gender": "undetermined", "followers_count": 1351, "location": "Belgique", "statuses_count": 2525, "id": 781533430576275456}, "sonianoneka": {"lang": "es", "favourites_count": 426, "name": "sonia villanueva", "friends_count": 462, "gender": "female", "followers_count": 438, "location": "", "statuses_count": 1408, "id": 146144115}, "ladynightmare_2": {"lang": "en", "favourites_count": 184, "name": "Cristina", "friends_count": 156, "gender": "female", "followers_count": 126, "location": "", "statuses_count": 644, "id": 706098229360926721}, "atrandafir": {"lang": "es", "favourites_count": 377, "name": "Alexandru Trandafir", "friends_count": 2403, "gender": "male", "followers_count": 932, "location": "Barcelona", "statuses_count": 1694, "id": 17621153}, "FlamenQuino": {"lang": "es", "favourites_count": 1641, "name": "Quino", "friends_count": 348, "gender": "undetermined", "followers_count": 196, "location": "0x4de16c616761", "statuses_count": 10468, "id": 396811761}, "DaintyKitchen": {"lang": "en", "favourites_count": 0, "name": "The Dainty Kitchen", "friends_count": 88, "gender": "mostly_female", "followers_count": 8, "location": "England, United Kingdom", "statuses_count": 4, "id": 750430161317818368}, "avocode": {"lang": "en", "favourites_count": 530, "name": "Avocode", "friends_count": 549, "gender": "undetermined", "followers_count": 2094, "location": "Prague", "statuses_count": 1246, "id": 2534636804}, "ccbcorcoles": {"lang": "es", "favourites_count": 45, "name": "Carlos C\u00f3rcoles", "friends_count": 474, "gender": "male", "followers_count": 238, "location": "", "statuses_count": 987, "id": 143561961}, "chainisway": {"lang": "es", "favourites_count": 1098, "name": "C\u00e9sar Rodr\u00edguez", "friends_count": 534, "gender": "male", "followers_count": 174, "location": "", "statuses_count": 586, "id": 249462966}, "_uxarticle": {"lang": "es", "favourites_count": 7, "name": "uxarticle", "friends_count": 246, "gender": "undetermined", "followers_count": 50, "location": "Palma, Islas Baleares", "statuses_count": 34, "id": 4172110396}, "myLotHero": {"lang": "en", "favourites_count": 180, "name": "Josh Sedivy", "friends_count": 1947, "gender": "male", "followers_count": 2358, "location": "Saint Louis, MO", "statuses_count": 163, "id": 3061746187}, "SaysHummingbird": {"lang": "en", "favourites_count": 4705, "name": "The Hummingbird", "friends_count": 36129, "gender": "mostly_female", "followers_count": 54243, "location": "", "statuses_count": 2827, "id": 810619093749559296}, "FourLai": {"lang": "zh-cn", "favourites_count": 50, "name": "Servo Robotics", "friends_count": 4954, "gender": "undetermined", "followers_count": 572, "location": "\u4e2d\u534e\u4eba\u6c11\u5171\u548c\u56fd", "statuses_count": 128, "id": 773422958979219456}, "RLadiesMAD": {"lang": "en", "favourites_count": 202, "name": "R-Ladies Madrid", "friends_count": 320, "gender": "undetermined", "followers_count": 466, "location": "Madrid, Spain", "statuses_count": 755, "id": 772203134269652992}, "AptaMalaga": {"lang": "es", "favourites_count": 838, "name": "APTA M\u00c1LAGA", "friends_count": 654, "gender": "undetermined", "followers_count": 390, "location": "M\u00e1laga, Espa\u00f1a", "statuses_count": 718, "id": 3145616399}, "estrellavaca": {"lang": "es", "favourites_count": 1, "name": "Estrella Vaca", "friends_count": 96, "gender": "female", "followers_count": 31, "location": "Seville", "statuses_count": 62, "id": 47968978}, "camaraabierta": {"lang": "en", "favourites_count": 908, "name": "C\u00e1mara abierta 2.0", "friends_count": 655, "gender": "undetermined", "followers_count": 19802, "location": "TVE", "statuses_count": 2321, "id": 52823380}, "vuihocweb": {"lang": "en", "favourites_count": 164, "name": "Vuihocweb", "friends_count": 4900, "gender": "undetermined", "followers_count": 1044, "location": "Vietnam", "statuses_count": 267, "id": 717656019061460992}, "Vanessa09870475": {"lang": "en", "favourites_count": 998, "name": "Crystal Bell", "friends_count": 988, "gender": "female", "followers_count": 18, "location": "", "statuses_count": 2, "id": 854787425616498688}, "ElhornodeJuan": {"lang": "es", "favourites_count": 1, "name": "El horno de Juan", "friends_count": 1060, "gender": "mostly_female", "followers_count": 100, "location": "Churriana de la Vega, Espa\u00f1a", "statuses_count": 6, "id": 818750507120492544}, "campanilla": {"lang": "es", "favourites_count": 2788, "name": "Campanilla", "friends_count": 462, "gender": "undetermined", "followers_count": 504, "location": "", "statuses_count": 10654, "id": 6476132}, "lorenapaz": {"lang": "en", "favourites_count": 52, "name": "lorenapaz", "friends_count": 1893, "gender": "undetermined", "followers_count": 595, "location": "Net", "statuses_count": 274, "id": 15717384}, "NachoMachiina": {"lang": "es", "favourites_count": 430, "name": "Nacho", "friends_count": 554, "gender": "male", "followers_count": 301, "location": "Madrid, Espa\u00f1a", "statuses_count": 572, "id": 781167919862517760}, "RADARmalaga": {"lang": "es", "favourites_count": 61, "name": "RADAR // M\u00e1laga", "friends_count": 1000, "gender": "undetermined", "followers_count": 229, "location": "M\u00e1laga", "statuses_count": 148, "id": 771010952200355840}, "Alasdiel": {"lang": "es", "favourites_count": 1766, "name": "Lau", "friends_count": 304, "gender": "male", "followers_count": 149, "location": "Omicron Persei 8", "statuses_count": 1285, "id": 3150684699}, "Maribelsquare": {"lang": "es", "favourites_count": 77, "name": "Isabel Ram\u00edrez", "friends_count": 88, "gender": "female", "followers_count": 95, "location": "", "statuses_count": 150, "id": 1544902110}, "olea": {"lang": "es", "favourites_count": 13843, "name": "Ismael Olea", "friends_count": 510, "gender": "male", "followers_count": 1577, "location": "Almer\u00eda", "statuses_count": 35912, "id": 2170361}, "annacobos": {"lang": "es", "favourites_count": 137, "name": "Anna Cobos", "friends_count": 735, "gender": "female", "followers_count": 398, "location": "Bilbao", "statuses_count": 542, "id": 62484717}, "mokutoweb": {"lang": "es", "favourites_count": 40, "name": "Mokuto", "friends_count": 369, "gender": "undetermined", "followers_count": 205, "location": "Palma, Espa\u00f1a", "statuses_count": 217, "id": 774200398060158976}, "sergiorios": {"lang": "es", "favourites_count": 68, "name": "Sergio R\u00edos", "friends_count": 105, "gender": "male", "followers_count": 492, "location": "Madrid", "statuses_count": 772, "id": 39245959}, "acamposserna": {"lang": "es", "favourites_count": 1097, "name": "Antonio Campos Serna", "friends_count": 961, "gender": "male", "followers_count": 607, "location": "Alicante", "statuses_count": 3501, "id": 284629216}, "juanferrub": {"lang": "es", "favourites_count": 1251, "name": "Juan Fern\u00e1ndez", "friends_count": 3763, "gender": "male", "followers_count": 2121, "location": "Madrid, Spain", "statuses_count": 3805, "id": 119666649}, "frank_erlich": {"lang": "es", "favourites_count": 176, "name": "Pancho", "friends_count": 373, "gender": "male", "followers_count": 1483, "location": "madrid", "statuses_count": 290, "id": 141132983}, "ain_infographic": {"lang": "ar", "favourites_count": 369, "name": "Ain Infographic", "friends_count": 4488, "gender": "male", "followers_count": 1289, "location": "Syria", "statuses_count": 368, "id": 3188258542}, "JMChia": {"lang": "es", "favourites_count": 2235, "name": "Jos\u00e9 M. Chia", "friends_count": 7881, "gender": "mostly_female", "followers_count": 22414, "location": "Andaluc\u00eda \u2192 Madrid ", "statuses_count": 12875, "id": 78954366}, "MalagaViz": {"lang": "es", "favourites_count": 2, "name": "M\u00e1lagaVIZ", "friends_count": 56, "gender": "undetermined", "followers_count": 59, "location": "M\u00e1laga, Espa\u00f1a", "statuses_count": 120, "id": 758213447985364992}, "VisitasReales": {"lang": "es", "favourites_count": 0, "name": "\ud83d\ude80Visitas Reales", "friends_count": 38377, "gender": "undetermined", "followers_count": 48704, "location": "Espa\u00f1a", "statuses_count": 4211, "id": 4296162136}, "XtremisDE": {"lang": "de", "favourites_count": 56, "name": "XtremisDE", "friends_count": 127, "gender": "undetermined", "followers_count": 26, "location": "Barcelona, Spanien", "statuses_count": 31, "id": 776345089652195329}, "UXTopNews": {"lang": "en", "favourites_count": 694, "name": "UX Top News", "friends_count": 4842, "gender": "undetermined", "followers_count": 1154, "location": "", "statuses_count": 6375, "id": 4544337013}, "jlmoyac": {"lang": "es", "favourites_count": 1509, "name": "Jose Luis Moya C.", "friends_count": 1078, "gender": "male", "followers_count": 547, "location": "al sur", "statuses_count": 7914, "id": 65027213}, "gines_lg": {"lang": "es", "favourites_count": 174, "name": "Gin\u00e9s L\u00f3pez", "friends_count": 520, "gender": "male", "followers_count": 114, "location": "", "statuses_count": 304, "id": 2828161549}, "tosqui100": {"lang": "es", "favourites_count": 7979, "name": "Sergio\u277e\u00be", "friends_count": 874, "gender": "male", "followers_count": 152, "location": "Hogwarts ", "statuses_count": 4244, "id": 4384087816}, "C0conudo": {"lang": "en", "favourites_count": 218, "name": "C0co", "friends_count": 317, "gender": "undetermined", "followers_count": 128, "location": "Madrid", "statuses_count": 2100, "id": 32352373}, "sueos20131": {"lang": "es", "favourites_count": 2, "name": "celebraciones sue\u00f1os", "friends_count": 744, "gender": "undetermined", "followers_count": 62, "location": "", "statuses_count": 6, "id": 801830340910256128}, "0ceryrade": {"lang": "es", "favourites_count": 1144, "name": "Ruina", "friends_count": 12364, "gender": "undetermined", "followers_count": 26042, "location": "MAD", "statuses_count": 45, "id": 2940831993}, "Estebansalgadox": {"lang": "es", "favourites_count": 34, "name": "Esteban salgado", "friends_count": 805, "gender": "male", "followers_count": 65, "location": "", "statuses_count": 91, "id": 1505278464}, "BarbaneroJavier": {"lang": "en", "favourites_count": 1628, "name": "javier martin", "friends_count": 832, "gender": "mostly_male", "followers_count": 448, "location": "Barcelona", "statuses_count": 2747, "id": 559504482}, "AdrianVerdau": {"lang": "es", "favourites_count": 283, "name": "Adrian Verdau\ud83d\ude03", "friends_count": 369, "gender": "male", "followers_count": 250, "location": "Buenos Aires - Argentina", "statuses_count": 1107, "id": 598808251}, "susanpinzon": {"lang": "es", "favourites_count": 256, "name": "Susana Pinz\u00f3n", "friends_count": 142, "gender": "female", "followers_count": 99, "location": "", "statuses_count": 662, "id": 289289967}, "sserafinelli": {"lang": "es", "favourites_count": 143, "name": "Stefano Serafinelli", "friends_count": 394, "gender": "male", "followers_count": 355, "location": "Madrid", "statuses_count": 374, "id": 496817364}, "patri_pe": {"lang": "es", "favourites_count": 2749, "name": "Patricia Perochena", "friends_count": 601, "gender": "female", "followers_count": 427, "location": "republica de la casqueria ", "statuses_count": 6102, "id": 95056494}, "karol_depka": {"lang": "en", "favourites_count": 61, "name": "Karol Depka Pr.", "friends_count": 119, "gender": "male", "followers_count": 23, "location": "M\u00e1laga", "statuses_count": 74, "id": 399692381}, "PoloDigitalMLG": {"lang": "es", "favourites_count": 882, "name": "Polo Digital M\u00e1laga", "friends_count": 651, "gender": "male", "followers_count": 859, "location": "M\u00e1laga, Andaluc\u00eda", "statuses_count": 1180, "id": 781829562858663936}, "iclaudia00": {"lang": "es", "favourites_count": 48, "name": "Claudia I.", "friends_count": 2093, "gender": "female", "followers_count": 282, "location": "Madrid", "statuses_count": 8, "id": 529060166}, "wecodesign": {"lang": "es", "favourites_count": 173, "name": "WeCodeSign Podcast", "friends_count": 27, "gender": "undetermined", "followers_count": 534, "location": "#Podcasting", "statuses_count": 465, "id": 706563460583260160}, "LaWorkeria": {"lang": "en", "favourites_count": 93, "name": "La Workeria", "friends_count": 2551, "gender": "undetermined", "followers_count": 565, "location": "M\u00e1laga, Espa\u00f1a", "statuses_count": 118, "id": 786905060710158336}, "Hexaedron": {"lang": "es", "favourites_count": 1, "name": "Hexaedron", "friends_count": 55, "gender": "undetermined", "followers_count": 5, "location": "M\u00e1laga (Spain)", "statuses_count": 35, "id": 2315369754}, "javiercanada": {"lang": "es", "favourites_count": 5543, "name": "Javier Ca\u00f1ada", "friends_count": 461, "gender": "mostly_male", "followers_count": 1413, "location": "", "statuses_count": 3163, "id": 2582764214}, "male_count": 71, "pberbel": {"lang": "en", "favourites_count": 719, "name": "Patricio Berbel", "friends_count": 1638, "gender": "male", "followers_count": 816, "location": "M\u00e1laga, Spain", "statuses_count": 1514, "id": 38049355}, "MestiriSarah": {"lang": "fr", "favourites_count": 497, "name": "Sarah Mestiri", "friends_count": 378, "gender": "female", "followers_count": 258, "location": "Tunisie", "statuses_count": 353, "id": 417005772}, "rheannamartinez": {"lang": "en", "favourites_count": 4337, "name": "Rheanna Martinez", "friends_count": 1816, "gender": "undetermined", "followers_count": 1123, "location": "San Francisco / SLO", "statuses_count": 11888, "id": 22499102}, "ciberado": {"lang": "es", "favourites_count": 8932, "name": "Javi Moreno", "friends_count": 510, "gender": "undetermined", "followers_count": 1916, "location": "", "statuses_count": 10194, "id": 132851687}, "nan_karuthan": {"lang": "en", "favourites_count": 54, "name": "ilanthendral r", "friends_count": 51, "gender": "undetermined", "followers_count": 15, "location": "", "statuses_count": 59, "id": 2516271961}, "froums": {"lang": "fr", "favourites_count": 82, "name": "Farouk Zaidi", "friends_count": 337, "gender": "male", "followers_count": 94, "location": "", "statuses_count": 221, "id": 225376301}, "lmglobetrotter": {"lang": "en", "favourites_count": 222, "name": "LMissGlobeTrotter", "friends_count": 236, "gender": "undetermined", "followers_count": 89, "location": "", "statuses_count": 374, "id": 3082148018}, "manelmourning": {"lang": "en", "favourites_count": 3281, "name": "Manel Abella", "friends_count": 520, "gender": "male", "followers_count": 334, "location": "Madrid / Barcelona", "statuses_count": 2169, "id": 3365611043}, "IgnaciodeNuevo": {"lang": "es", "favourites_count": 517, "name": "Ignacio Villanueva", "friends_count": 454, "gender": "male", "followers_count": 580, "location": "Madrid, Spain", "statuses_count": 5235, "id": 2730132444}, "undefined_count": 83, "unintendedbear": {"lang": "es", "favourites_count": 5313, "name": "Paloma de las Cuevas", "friends_count": 582, "gender": "female", "followers_count": 631, "location": "Granada", "statuses_count": 23445, "id": 300195350}, "Laura_Morillo": {"lang": "es", "favourites_count": 443, "name": "Laura Morillo", "friends_count": 359, "gender": "female", "followers_count": 1398, "location": "Madrid", "statuses_count": 3587, "id": 85189725}, "JuanDiazGalind2": {"lang": "es", "favourites_count": 0, "name": "Juan Diaz Galindo", "friends_count": 93, "gender": "male", "followers_count": 6, "location": "", "statuses_count": 0, "id": 762703161048100866}, "emilio_alcalde": {"lang": "es", "favourites_count": 458, "name": "Emilio Alcalde", "friends_count": 423, "gender": "male", "followers_count": 276, "location": "", "statuses_count": 939, "id": 248680033}, "KreativaClub": {"lang": "es", "favourites_count": 4, "name": "Kreativa People", "friends_count": 496, "gender": "undetermined", "followers_count": 68, "location": "Torremolinos, Espa\u00f1a", "statuses_count": 5, "id": 825330407323422722}, "Eudaric": {"lang": "es", "favourites_count": 2175, "name": "M 2.0", "friends_count": 291, "gender": "undetermined", "followers_count": 345, "location": "Mis borderias", "statuses_count": 27092, "id": 116771556}, "mm_tr": {"lang": "en", "favourites_count": 530, "name": "Miguel Torres", "friends_count": 92, "gender": "male", "followers_count": 85, "location": "M\u00e1laga", "statuses_count": 1130, "id": 317378321}, "EduCabellos": {"lang": "es", "favourites_count": 64, "name": "Edu Cabellos", "friends_count": 845, "gender": "undetermined", "followers_count": 1770, "location": "Palma de Mallorca", "statuses_count": 26766, "id": 403275931}, "t0tinspire": {"lang": "es", "favourites_count": 5787, "name": "Sergio For\u00e9s", "friends_count": 4103, "gender": "male", "followers_count": 821, "location": "Barcelona, Espa\u00f1a", "statuses_count": 4761, "id": 59100345}, "lciniesta": {"lang": "es", "favourites_count": 118, "name": "Luis Ca\u00f1as Iniesta", "friends_count": 73, "gender": "male", "followers_count": 54, "location": "M\u00e1laga, Espa\u00f1a", "statuses_count": 508, "id": 194624077}, "raquepe": {"lang": "es", "favourites_count": 347, "name": "raquepe", "friends_count": 740, "gender": "undetermined", "followers_count": 257, "location": "Seville (Spain)", "statuses_count": 412, "id": 402720503}, "mcmosso": {"lang": "es", "favourites_count": 9, "name": "mcm", "friends_count": 195, "gender": "undetermined", "followers_count": 146, "location": "C\u00f3rdoba. Argentina.", "statuses_count": 434, "id": 302636833}}, "nonbinary_count": 161}}